word_to_txt_mcp/__init__.py
word_to_txt_mcp/cli.py
word_to_txt_mcp/server.py
word_to_txt_mcp-0.1.0.dist-info/licenses/LICENSE
word_to_txt_mcp-0.1.0.dist-info/METADATA
word_to_txt_mcp-0.1.0.dist-info/WHEEL
word_to_txt_mcp-0.1.0.dist-info/entry_points.txt
word_to_txt_mcp-0.1.0.dist-info/top_level.txt
word_to_txt_mcp-0.1.0.dist-info/RECORD
