Metadata-Version: 2.4
Name: word-to-txt-mcp
Version: 0.1.0
Summary: FastMCP Word文档转文本分析服务器
Home-page: https://github.com/yourusername/word-to-txt-mcp
Author: Your Name
Author-email: Your Name <your.email@example.com>
License: MIT
Project-URL: Homepage, https://github.com/yourusername/word-to-txt-mcp
Project-URL: Bug Reports, https://github.com/yourusername/word-to-txt-mcp/issues
Project-URL: Source, https://github.com/yourusername/word-to-txt-mcp
Project-URL: Documentation, https://github.com/yourusername/word-to-txt-mcp#readme
Keywords: mcp,fastmcp,word,document,text,analysis,docx,conversion,server,api
Classifier: Development Status :: 3 - Alpha
Classifier: Intended Audience :: Developers
Classifier: Topic :: Software Development :: Libraries :: Python Modules
Classifier: Topic :: Text Processing :: General
Classifier: Topic :: Office/Business :: Office Suites
Classifier: License :: OSI Approved :: MIT License
Classifier: Programming Language :: Python :: 3
Classifier: Programming Language :: Python :: 3.8
Classifier: Programming Language :: Python :: 3.9
Classifier: Programming Language :: Python :: 3.10
Classifier: Programming Language :: Python :: 3.11
Classifier: Programming Language :: Python :: 3.12
Classifier: Operating System :: OS Independent
Requires-Python: >=3.8
License-File: LICENSE
Requires-Dist: fastmcp>=0.1.0
Requires-Dist: python-docx>=0.8.11
Provides-Extra: dev
Requires-Dist: pytest>=6.0; extra == "dev"
Requires-Dist: pytest-cov>=2.0; extra == "dev"
Requires-Dist: black>=21.0; extra == "dev"
Requires-Dist: flake8>=3.8; extra == "dev"
Requires-Dist: mypy>=0.800; extra == "dev"
Provides-Extra: test
Requires-Dist: pytest>=6.0; extra == "test"
Requires-Dist: pytest-cov>=2.0; extra == "test"
Dynamic: author
Dynamic: home-page
Dynamic: license-file
Dynamic: requires-python
